dhi/platform/__init__.py
dhi/platform/_version.py
dhi/platform/args.py
dhi/platform/authentication.py
dhi/platform/commonmodels.py
dhi/platform/config.py
dhi/platform/engine.py
dhi/platform/enginehelper.py
dhi/platform/eventing.py
dhi/platform/eventinghelper.py
dhi/platform/fmt.py
dhi/platform/gis.py
dhi/platform/job.py
dhi/platform/metadata.py
dhi/platform/metadatahelper.py
dhi/platform/multidimensional.py
dhi/platform/pubsub.py
dhi/platform/raw.py
dhi/platform/rawhelper.py
dhi/platform/sharing.py
dhi/platform/tiles.py
dhi/platform/timeseries.py
dhi/platform/timeserieshelper.py
dhi/platform/transfer.py
dhi/platform/transferhelper.py
dhi/platform/base/client.py
dhi/platform/base/constants.py
dhi/platform/base/exceptions.py
dhi/platform/base/utils.py
dhi/platform/cli/help.py
dhi/platform/cli/cfg/login.py
dhi/platform/cli/ds/append.py
dhi/platform/cli/ds/convert.py
dhi/platform/cli/ds/cp.py
dhi/platform/cli/ds/cpbh.py
dhi/platform/cli/ds/cph.py
dhi/platform/cli/ds/download.py
dhi/platform/cli/ds/downloadc.py
dhi/platform/cli/ds/info.py
dhi/platform/cli/ds/infor.py
dhi/platform/cli/ds/ls.py
dhi/platform/cli/ds/lsh.py
dhi/platform/cli/ds/lsra.py
dhi/platform/cli/ds/restore.py
dhi/platform/cli/ds/rm.py
dhi/platform/cli/ds/rmhard.py
dhi/platform/cli/ds/update.py
dhi/platform/cli/ds/upload.py
dhi/platform/cli/ds/uploadstaged.py
dhi/platform/cli/eng/cancel.py
dhi/platform/cli/eng/configurations.py
dhi/platform/cli/eng/diag.py
dhi/platform/cli/eng/engine.py
dhi/platform/cli/eng/engines.py
dhi/platform/cli/eng/info.py
dhi/platform/cli/eng/input.py
dhi/platform/cli/eng/list.py
dhi/platform/cli/eng/listmy.py
dhi/platform/cli/eng/rm.py
dhi/platform/cli/eng/run.py
dhi/platform/cli/eng/runp.py
dhi/platform/cli/eng/sbmessages.py
dhi/platform/cli/gw/service.py
dhi/platform/cli/gw/services.py
dhi/platform/cli/prj/capabilities.py
dhi/platform/cli/prj/create.py
dhi/platform/cli/prj/createsub.py
dhi/platform/cli/prj/info.py
dhi/platform/cli/prj/infor.py
dhi/platform/cli/prj/ls.py
dhi_platform-1.0.10.dist-info/LICENSE
dhi_platform-1.0.10.dist-info/METADATA
dhi_platform-1.0.10.dist-info/WHEEL
dhi_platform-1.0.10.dist-info/top_level.txt
dhi_platform-1.0.10.dist-info/RECORD
