Metadata-Version: 2.1
Name: dhi-platform
Version: 1.0.10
Summary: MIKE Cloud Platform SDK for Python
Home-page: https://develop.mike-cloud.com/
Author: DHI
Author-email: wdpservice@dhigroup.com
License: MIT License
Project-URL: Open API, https://develop.mike-cloud.com/swagger/index.html
Project-URL: Documentation, https://develop.mike-cloud.com/docs/
Classifier: License :: OSI Approved :: MIT License
Classifier: Development Status :: 4 - Beta
Classifier: Intended Audience :: Science/Research
Classifier: Programming Language :: Python
Classifier: Programming Language :: Python :: 3
Classifier: Programming Language :: Python :: 3.8
Classifier: Programming Language :: Python :: 3.9
Classifier: Programming Language :: Python :: 3.10
Classifier: Programming Language :: Python :: 3.11
Classifier: Operating System :: OS Independent
Classifier: Topic :: Scientific/Engineering
Requires-Python: >=3.8
License-File: LICENSE
Requires-Dist: azure-identity >=1.6.0
Requires-Dist: azure-storage-blob >=12.8.1
Requires-Dist: PyYAML >=5.4.1
Requires-Dist: pandas
Requires-Dist: attrs
Requires-Dist: signalrcore >=0.9.5
Requires-Dist: signalr-async >=3.0.0
